c_build.py
morphomath/__init__.py
morphomath/factorization.py
morphomath/kernel.py
morphomath/subdivision.py
morphomath/template.c
morphomath/utils.py
morphomath-0.0.dev1.dist-info/licenses/LICENSE
morphomath-0.0.dev1.dist-info/METADATA
morphomath-0.0.dev1.dist-info/WHEEL
morphomath-0.0.dev1.dist-info/entry_points.txt
morphomath-0.0.dev1.dist-info/top_level.txt
morphomath-0.0.dev1.dist-info/RECORD
