Metadata-Version: 2.4
Name: morphomath
Version: 0.0.dev1
Summary: fast morphology using kernel subdivision
Author-email: "Robin RICHARD (robinechuca)" <serveurpython.oz@gmail.com>
Maintainer-email: "Robin RICHARD (robinechuca)" <serveurpython.oz@gmail.com>
License:                     GNU AFFERO GENERAL PUBLIC LICENSE
Project-URL: Homepage, https://framagit.org/robinechuca/morphomath/-/blob/main/README.rst
Project-URL: Documentation, https://morphomath.readthedocs.io/latest/
Project-URL: Repository, https://framagit.org/robinechuca/morphomath/
Project-URL: Changelog, https://framagit.org/robinechuca/morphomath/-/blob/main/docs/changelog.rst
Keywords: cse,dilatation,erosion,kernel subdivision,morpho,morphology,morphomath
Classifier: Development Status :: 3 - Alpha
Classifier: Natural Language :: English
Classifier: Operating System :: POSIX :: Linux
Classifier: Programming Language :: C
Classifier: Programming Language :: Python :: 3
Classifier: Topic :: Multimedia :: Graphics :: 3D Modeling
Classifier: Topic :: Scientific/Engineering :: Image Processing
Requires-Python: <3.14,>=3.11
License-File: LICENSE
Requires-Dist: networkx>=3.0
Requires-Dist: numpy>=2.0
Requires-Dist: tqdm
Provides-Extra: test
Requires-Dist: colour-science; extra == "test"
Requires-Dist: pydocstyle<=6.1.1; extra == "test"
Requires-Dist: pylama[all,toml]; extra == "test"
Requires-Dist: pytest; extra == "test"
Dynamic: license-file
